validate_actions/__init__.py
validate_actions/cli.py
validate_actions/cli_components/__init__.py
validate_actions/cli_components/output_formatter.py
validate_actions/cli_components/result_aggregator.py
validate_actions/domain_model/__init__.py
validate_actions/domain_model/ast.py
validate_actions/domain_model/contexts.py
validate_actions/domain_model/job_order_models.py
validate_actions/domain_model/primitives.py
validate_actions/globals/__init__.py
validate_actions/globals/cli_config.py
validate_actions/globals/fixer.py
validate_actions/globals/problems.py
validate_actions/globals/process_stage.py
validate_actions/globals/validation_result.py
validate_actions/globals/web_fetcher.py
validate_actions/main.py
validate_actions/pipeline.py
validate_actions/pipeline_stages/__init__.py
validate_actions/pipeline_stages/builder.py
validate_actions/pipeline_stages/builders/__init__.py
validate_actions/pipeline_stages/builders/events_builder.py
validate_actions/pipeline_stages/builders/interfaces.py
validate_actions/pipeline_stages/builders/jobs_builder.py
validate_actions/pipeline_stages/builders/shared_components_builder.py
validate_actions/pipeline_stages/builders/steps_builder.py
validate_actions/pipeline_stages/builders/workflow_builder.py
validate_actions/pipeline_stages/job_orderer.py
validate_actions/pipeline_stages/marketplace_enricher.py
validate_actions/pipeline_stages/parser.py
validate_actions/pipeline_stages/validator.py
validate_actions/rules/__init__.py
validate_actions/rules/action_input.py
validate_actions/rules/action_output.py
validate_actions/rules/action_version.py
validate_actions/rules/expressions_contexts.py
validate_actions/rules/rule.py
validate_actions/rules/rules.yml
validate_actions-1.0.6.dist-info/METADATA
validate_actions-1.0.6.dist-info/WHEEL
validate_actions-1.0.6.dist-info/entry_points.txt
validate_actions-1.0.6.dist-info/licenses/LICENSE
validate_actions-1.0.6.dist-info/RECORD
